README.md
setup.py
CJLTools/__init__.py
CJLTools/ioTools.py
CJLTools.egg-info/PKG-INFO
CJLTools.egg-info/SOURCES.txt
CJLTools.egg-info/dependency_links.txt
CJLTools.egg-info/requires.txt
CJLTools.egg-info/top_level.txt